[
  {
    "projectName": "Intuit Quickbooks INDIA",
    "designation": "Senior Software Engineer",
    "link": "https://quickbooks.intuit.com/",
    "cover": "",
    "skills": "ReactJS,  JavaScript, TypeScript, Styled Components, Material Ui",
    "companyName": "Intuit",
    "startDate": "2015-12-04",
    "endDate": "2020-06-04",
    "imageUrl": "https://raw.githubusercontent.com/DeepakPahawa/deepk-portfolio/master/images/1733253341479-Intuit%20Quickbooks.png"
  },
  {
    "projectName": "",
    "designation": "",
    "link": "",
    "cover": "",
    "skills": [],
    "companyName": "",
    "startDate": "",
    "endDate": "",
    "imageUrl": ""
  }
]